llm_completion/__init__.py
llm_completion/__main__.py
llm_completion/base.py
llm_completion/completion.py
llm_completion/component_processor.py
llm_completion/config.py
llm_completion/exceptions.py
llm_completion/logger.py
llm_completion/tag_manager.py
llm_completion/utils.py
llm_completion/cli/__init__.py
llm_completion/cli/component_tool.py
llm_completion/cli/tag_tool.py
llm_completion/implementations/__init__.py
llm_completion/implementations/json_generator.py
llm_completion/implementations/landing_tags.py
llm_completion/implementations/shadcn_to_ts.py
llm_completion/resources/__init__.py
llm_completion/resources/tag_data.py
llm_completion-0.1.8.dist-info/METADATA
llm_completion-0.1.8.dist-info/WHEEL
llm_completion-0.1.8.dist-info/top_level.txt
llm_completion-0.1.8.dist-info/RECORD
